louvijan/__init__.py
louvijan/pipe.py
louvijan/manager/__init__.py
louvijan/manager/base.py
louvijan/manager/config.py
louvijan/manager/execution.py
louvijan/manager/log.py
louvijan/manager/mail.py
louvijan/manager/remote.py
louvijan-0.1.3.dist-info/LICENSE
louvijan-0.1.3.dist-info/METADATA
louvijan-0.1.3.dist-info/WHEEL
louvijan-0.1.3.dist-info/top_level.txt
louvijan-0.1.3.dist-info/RECORD
