Metadata-Version: 2.1
Name: louvijan
Version: 0.1.3
Summary: A tool to control the script pipeline, which means that scripts can be executed in a specified order.
Home-page: https://github.com/TanyeeZhang/louvijan
Author: Tanyee Zhang
Author-email: 676761828@qq.com
License: UNKNOWN
Platform: UNKNOWN
Classifier: Programming Language :: Python :: 3
Classifier: License :: OSI Approved :: MIT License
Classifier: Operating System :: OS Independent
